voraus_logging_lib/__init__.py
voraus_logging_lib/constants.py
voraus_logging_lib/logging.py
voraus_logging_lib/py.typed
voraus_logging_lib-2.0.0.dist-info/licenses/LICENSE.txt
voraus_logging_lib-2.0.0.dist-info/METADATA
voraus_logging_lib-2.0.0.dist-info/WHEEL
voraus_logging_lib-2.0.0.dist-info/top_level.txt
voraus_logging_lib-2.0.0.dist-info/RECORD
